CurseForgeAPy/CFAPI.py
CurseForgeAPy/SchemaClasses.py
CurseForgeAPy/Utils.py
CurseForgeAPy/__init__.py
CurseForgeAPy-1.1.5.dist-info/LICENSE.md
CurseForgeAPy-1.1.5.dist-info/METADATA
CurseForgeAPy-1.1.5.dist-info/WHEEL
CurseForgeAPy-1.1.5.dist-info/top_level.txt
CurseForgeAPy-1.1.5.dist-info/RECORD
